lnac/__init__.py
lnac/ast.py
lnac/generator.py
lnac/lexer.py
lnac/main.py
lnac/nodes.py
lnac/parser.py
lnac/tokens.py
lnac-0.0.9.dist-info/METADATA
lnac-0.0.9.dist-info/RECORD
lnac-0.0.9.dist-info/WHEEL
lnac-0.0.9.dist-info/entry_points.txt
lnac-0.0.9.dist-info/top_level.txt
