Metadata-Version: 2.1
Name: lnac
Version: 0.0.9
Summary: A toy functional language compiler written in Python
Home-page: https://github.com/typicaltuesday/lna
Author: Lena
Author-email: typicaltuedsay@gmail.com
License: Apache License 2.0
